{
  "$schema": "https://ui.shadcn.com/schema/registry-item.json",
  "name": "dock",
  "type": "registry:component",
  "files": [
    {
      "path": "dock/dock.tsx",
      "type": "registry:component",
      "content": "'use client'\nimport { getLinkComponent, useSignals } from '@cascivo/core'\nimport { builtin, t } from '@cascivo/i18n'\nimport styles from './dock.module.css'\n\nexport interface DockItem {\n  label: string\n  icon: React.ReactNode\n  onClick?: () => void\n  href?: string\n}\n\nexport interface DockProps {\n  items: DockItem[]\n  activeIndex?: number\n  className?: string\n  /** Accessible label for the nav landmark */\n  ariaLabel?: string\n}\n\nexport function Dock({ items, activeIndex, className, ariaLabel }: DockProps) {\n  useSignals()\n  const resolvedAriaLabel = ariaLabel ?? t(builtin.dock.nav)\n  return (\n    <nav\n      aria-label={resolvedAriaLabel}\n      className={[styles.dock, className].filter(Boolean).join(' ')}\n    >\n      {items.map((item, i) => {\n        const isActive = i === activeIndex\n        const Tag = item.href ? getLinkComponent() : 'button'\n        return (\n          <Tag\n            key={i}\n            className={styles.item}\n            data-active={isActive || undefined}\n            aria-current={isActive ? 'page' : undefined}\n            {...(item.href ? { href: item.href } : {})}\n            type={item.href ? undefined : 'button'}\n            onClick={item.onClick}\n          >\n            <span className={styles.icon} aria-hidden=\"true\">\n              {item.icon}\n            </span>\n            <span className={styles.label}>{item.label}</span>\n          </Tag>\n        )\n      })}\n    </nav>\n  )\n}\n"
    },
    {
      "path": "dock/dock.module.css",
      "type": "registry:component",
      "content": "@layer cascivo.component {\n  .dock {\n    position: fixed;\n    inset-block-end: 0;\n    inset-inline: 0;\n    display: flex;\n    align-items: stretch;\n    background-color: var(--cascivo-color-surface);\n    border-block-start: 1px solid var(--cascivo-border-subtle);\n    padding-block-end: env(safe-area-inset-bottom, 0);\n    z-index: var(--cascivo-z-dock, 40);\n  }\n\n  @media (min-width: 64rem) {\n    .dock {\n      display: none;\n    }\n  }\n\n  .item {\n    display: flex;\n    flex-direction: column;\n    align-items: center;\n    justify-content: center;\n    flex: 1;\n    gap: 0.25rem;\n    padding-block: 0.5rem;\n    padding-inline: 0.25rem;\n    min-block-size: var(--cascivo-target-min-coarse, 2.75rem);\n    background: none;\n    border: none;\n    cursor: pointer;\n    color: var(--cascivo-color-text-muted);\n    text-decoration: none;\n    transition: color 100ms var(--cascivo-ease-out);\n  }\n\n  .item[data-active] {\n    color: var(--cascivo-color-accent);\n  }\n\n  .item:focus-visible {\n    outline: var(--cascivo-ring-width) solid var(--cascivo-ring-color);\n    outline-offset: -2px;\n  }\n\n  .icon {\n    display: flex;\n    align-items: center;\n    font-size: 1.25rem;\n    line-height: 1;\n  }\n\n  .label {\n    font-size: 0.6875rem;\n    line-height: 1;\n  }\n\n  .item[data-active] .label {\n    font-weight: 600;\n  }\n}\n"
    }
  ],
  "description": "Fixed bottom navigation bar for mobile app shells with up to 5 items",
  "dependencies": ["@cascivo/core", "@cascivo/i18n"],
  "categories": ["navigation"],
  "meta": {
    "cascivo": {
      "type": "component",
      "version": "0.8.0"
    }
  }
}
